CHANGELOG.md
floc/SortingLshClusters
floc/__init__.py
floc/floc_go/__init__.py
floc/floc_go/floc_go-darwin.h
floc/floc_go/floc_go-darwin.so
floc/floc_go/floc_go-linux.h
floc/floc_go/floc_go-linux.so
floc/go_types.py
floc/hashes.py
floc/py.typed
floc/simulate.py
floc/sorting.py
floc-0.4.0.dist-info/LICENSE
floc-0.4.0.dist-info/WHEEL
floc-0.4.0.dist-info/METADATA
floc-0.4.0.dist-info/RECORD
