Metadata-Version: 2.1
Name: floc
Version: 0.4.0
Summary: A floc simulator wrapper for Python over a Go implementation
Home-page: https://github.com/thepabloaguilar/floc
License: MIT
Keywords: floc,machine learning
Author: Pablo Aguilar
Author-email: pablo.aguilar@fatec.sp.gov.br
Requires-Python: >=3.7,<4.0
Classifier: Intended Audience :: Developers
Classifier: Intended Audience :: Science/Research
Classifier: License :: OSI Approved :: MIT License
Classifier: Programming Language :: Python :: 3
Classifier: Programming Language :: Python :: 3 :: Only
Classifier: Programming Language :: Python :: 3.7
Classifier: Programming Language :: Python :: 3.8
Classifier: Programming Language :: Python :: 3.9
Classifier: Topic :: Scientific/Engineering :: Artificial Intelligence
Project-URL: Bug Tracker, https://github.com/thepabloaguilar/floc/issues
Project-URL: Documentation, https://floc.readthedocs.io
Project-URL: Repository, https://github.com/thepabloaguilar/floc
